README.rst
setup.cfg
setup.py
astronomer/starship/operators.py
astronomer/starship/connections/operators.py
astronomer/starship/env/operators.py
astronomer/starship/variables/operators.py
astronomer_starship_provider.egg-info/PKG-INFO
astronomer_starship_provider.egg-info/SOURCES.txt
astronomer_starship_provider.egg-info/dependency_links.txt
astronomer_starship_provider.egg-info/namespace_packages.txt
astronomer_starship_provider.egg-info/requires.txt
astronomer_starship_provider.egg-info/top_level.txt