Metadata-Version: 1.2
Name: astronomer-starship-provider
Version: 0.1.3
Summary: Migration operators to assist moving variables, connections to Astronomer Cloud
Home-page: https://github.com/astronomer/starship/astronomer-starship-provider
Author: Astronomer CSE Team
License: UNKNOWN
Project-URL: Source Code, https://github.com/astronomer/starship/astronomer-starship-provider
Project-URL: Homepage, https://astronomer.io
Platform: UNKNOWN
Requires-Python: <4,>=3.7
